{
    "raw": "```JSON_RESULT\n{\n    \"intent_tree\": {\n        \"保存微信文章到电脑并验证链接有效性\": {\n            \"验证微信文章链接是否有效\": {},\n            \"保存微信文章内容到本地\": {}\n        }\n    },\n    \"task_graph\": {\n        \"nodes\": [\n            {\"id\": \"Node1\", \"description\": \"从微信复制文章链接\"},\n            {\"id\": \"Node2\", \"description\": \"在浏览器中粘贴URL以检查其有效性\"},\n            {\"id\": \"Node3\", \"description\": \"判断链接是否被限制在微信内打开\"},\n            {\"id\": \"Node4\", \"description\": \"判断链接是否已失效或无法访问\"},\n            {\"id\": \"Node5\", \"description\": \"通过Python代码发起HTTP请求验证链接\"},\n            {\"id\": \"Node6\", \"description\": \"将返回的HTML内容保存为本地文件\"},\n            {\"id\": \"Node7\", \"description\": \"使用微信内置功能保存文章到笔记\"},\n            {\"id\": \"Node8\", \"description\": \"通过截图或PDF工具导出文章内容\"}\n        ],\n        \"links\": [\n            {\"source\": \"Node1\", \"target\": \"Node2\", \"type\": \"inputLink\"},\n            {\"source\": \"Node2\", \"target\": \"Node3\", \"type\": \"checkRestriction\"},\n            {\"source\": \"Node2\", \"target\": \"Node4\", \"type\": \"checkValidity\"},\n            {\"source\": \"Node5\", \"target\": \"Node6\", \"type\": \"saveContent\"},\n            {\"source\": \"Node7\", \"target\": \"Node8\", \"type\": \"exportNotes\"}\n        ]\n    },\n    \"mapping\": {\n        \"保存微信文章到电脑并验证链接有效性\": {\n            \"nodes\": [\"Node1\", \"Node2\", \"Node3\", \"Node4\", \"Node5\", \"Node6\", \"Node7\", \"Node8\"]\n        },\n        \"验证微信文章链接是否有效\": {\n            \"nodes\": [\"Node1\", \"Node2\", \"Node3\", \"Node4\", \"Node5\"]\n        },\n        \"保存微信文章内容到本地\": {\n            \"nodes\": [\"Node6\", \"Node7\", \"Node8\"]\n        }\n    }\n}\n```",
    "intent_tree": "{\"保存微信文章到电脑并验证链接有效性\": {\"验证微信文章链接是否有效\": {}, \"保存微信文章内容到本地\": {}}}",
    "task_graph": "{\"nodes\": [{\"id\": \"Node1\", \"description\": \"从微信复制文章链接\"}, {\"id\": \"Node2\", \"description\": \"在浏览器中粘贴URL以检查其有效性\"}, {\"id\": \"Node3\", \"description\": \"判断链接是否被限制在微信内打开\"}, {\"id\": \"Node4\", \"description\": \"判断链接是否已失效或无法访问\"}, {\"id\": \"Node5\", \"description\": \"通过Python代码发起HTTP请求验证链接\"}, {\"id\": \"Node6\", \"description\": \"将返回的HTML内容保存为本地文件\"}, {\"id\": \"Node7\", \"description\": \"使用微信内置功能保存文章到笔记\"}, {\"id\": \"Node8\", \"description\": \"通过截图或PDF工具导出文章内容\"}], \"links\": [{\"source\": \"Node1\", \"target\": \"Node2\", \"type\": \"inputLink\"}, {\"source\": \"Node2\", \"target\": \"Node3\", \"type\": \"checkRestriction\"}, {\"source\": \"Node2\", \"target\": \"Node4\", \"type\": \"checkValidity\"}, {\"source\": \"Node5\", \"target\": \"Node6\", \"type\": \"saveContent\"}, {\"source\": \"Node7\", \"target\": \"Node8\", \"type\": \"exportNotes\"}]}",
    "mapping": "{\"保存微信文章到电脑并验证链接有效性\": {\"nodes\": [\"Node1\", \"Node2\", \"Node3\", \"Node4\", \"Node5\", \"Node6\", \"Node7\", \"Node8\"]}, \"验证微信文章链接是否有效\": {\"nodes\": [\"Node1\", \"Node2\", \"Node3\", \"Node4\", \"Node5\"]}, \"保存微信文章内容到本地\": {\"nodes\": [\"Node6\", \"Node7\", \"Node8\"]}}"
}