{
    "raw": "```JSON_RESULT\n{\n    \"intent_tree\": {\n        \"Find or access an article on WeChat\": {\n            \"Access an article using a direct link/URL\": {\n                \"Extract direct link from WeChat app\": {},\n                \"Validate and use the extracted link programmatically\": {\n                    \"Bypass login requirement for accessing WeChat articles\": {\n                        \"Use session cookies to authenticate requests\": {},\n                        \"Emulate WeChat client behavior to avoid security checks\": {}\n                    },\n                    \"Identify the start of the article content on the page\": {\n                        \"Search for prominent text blocks in the HTML structure\": {},\n                        \"Handle dynamic content loading and encrypted text blobs\": {}\n                    },\n                    \"Extract and save specific article components\": {\n                        \"Separate main title, subtitles (H2), and sub-subtitles (H3) from article content\": {\n                            \"Extract main title from the HTML structure\": {},\n                            \"Extract H2 subtitles from the HTML structure\": {},\n                            \"Extract H3 sub-subtitles from the HTML structure\": {}\n                        },\n                        \"Save extracted article data to a local file\": {\n                            \"Validate extracted components before saving\": {},\n                            \"Generate a structured output file with clean formatting\": {},\n                            \"Store the file in a user-accessible location\": {}\n                        }\n                    }\n                }\n            },\n            \"Search for an article using keywords or account names\": {},\n            \"Access an article from an official account (公众号)\": {}\n        }\n    },\n    \"task_graph\": {\n        \"nodes\": [\n            {\"id\": \"Node1\", \"description\": \"Share the direct link to a WeChat contact or use 'Share to WeChat' option in browser\"},\n            {\"id\": \"Node2\", \"description\": \"Open the shared link within WeChat’s in-app browser\"},\n            {\"id\": \"Node3\", \"description\": \"Use WeChat’s search bar to find articles by keywords, titles, or official account names\"},\n            {\"id\": \"Node4\", \"description\": \"Browse historical posts or use built-in search within an official account profile\"},\n            {\"id\": \"Node5\", \"description\": \"Use external tools like Sogou or WeChat Index for broader public article discovery\"},\n            {\"id\": \"Node6\", \"description\": \"Open the WeChat article and tap the ⋮ (three dots) to copy the direct link\"},\n            {\"id\": \"Node7\", \"description\": \"Programmatically validate and attempt to access the copied WeChat article link\"},\n            {\"id\": \"Node8\", \"description\": \"Extract session cookies from WeChat app using dynamic instrumentation tools\"},\n            {\"id\": \"Node9\", \"description\": \"Inject stolen cookies into HTTP requests to bypass login prompts\"},\n            {\"id\": \"Node10\", \"description\": \"Emulate WeChat client headers and device fingerprint to mimic legitimate access\"},\n            {\"id\": \"Node11\", \"description\": \"Parse the HTML structure to locate prominent text blocks (e.g., <div> with class 'rich_media_content')\"},\n            {\"id\": \"Node12\", \"description\": \"Handle cases where content is dynamically loaded or encrypted\"},\n            {\"id\": \"Node13\", \"description\": \"Extract and clean article text from identified HTML elements\"},\n            {\"id\": \"Node14\", \"description\": \"Extract main title from the HTML structure (e.g., <h1> tag)\"},\n            {\"id\": \"Node15\", \"description\": \"Extract subtitles from the HTML structure (e.g., <h2>, <h3> tags)\"},\n            {\"id\": \"Node16\", \"description\": \"Generate a structured output file with clean formatting\"},\n            {\"id\": \"Node17\", \"description\": \"Save the structured output file to a user-accessible location (e.g., Desktop)\"},\n            {\"id\": \"Node18\", \"description\": \"Notify the user of the exact file path where the output is saved\"},\n            {\"id\": \"Node19\", \"description\": \"Separate H2 subtitles from H3 sub-subtitles during extraction\"},\n            {\"id\": \"Node20\", \"description\": \"Validate extracted components (title, H2, H3, content) before saving\"},\n            {\"id\": \"Node21\", \"description\": \"Provide confirmation preview of extracted content before saving\"}\n        ],\n        \"links\": [\n            {\"source\": \"Node1\", \"target\": \"Node2\", \"type\": \"shareLink\"},\n            {\"source\": \"Node3\", \"target\": \"Node4\", \"type\": \"searchWithinAccount\"},\n            {\"source\": \"Node3\", \"target\": \"Node5\", \"type\": \"broadenSearch\"},\n            {\"source\": \"Node6\", \"target\": \"Node7\", \"type\": \"extractAndValidateLink\"},\n            {\"source\": \"Node8\", \"target\": \"Node9\", \"type\": \"cookieExtraction\"},\n            {\"source\": \"Node9\", \"target\": \"Node10\", \"type\": \"emulateClientBehavior\"},\n            {\"source\": \"Node7\", \"target\": \"Node11\", \"type\": \"parseHTMLForContent\"},\n            {\"source\": \"Node11\", \"target\": \"Node12\", \"type\": \"handleDynamicContent\"},\n            {\"source\": \"Node12\", \"target\": \"Node13\", \"type\": \"extractArticleText\"},\n            {\"source\": \"Node11\", \"target\": \"Node14\", \"type\": \"extractMainTitle\"},\n            {\"source\": \"Node11\", \"target\": \"Node15\", \"type\": \"extractSubtitles\"},\n            {\"source\": \"Node15\", \"target\": \"Node19\", \"type\": \"separateH2andH3\"},\n            {\"source\": \"Node14\", \"target\": \"Node20\", \"type\": \"validateComponents\"},\n            {\"source\": \"Node19\", \"target\": \"Node20\", \"type\": \"validateComponents\"},\n            {\"source\": \"Node13\", \"target\": \"Node20\", \"type\": \"validateComponents\"},\n            {\"source\": \"Node20\", \"target\": \"Node21\", \"type\": \"confirmationPreview\"},\n            {\"source\": \"Node21\", \"target\": \"Node16\", \"type\": \"generateStructuredOutput\"},\n            {\"source\": \"Node16\", \"target\": \"Node17\", \"type\": \"saveToFile\"},\n            {\"source\": \"Node17\", \"target\": \"Node18\", \"type\": \"notifyUserOfFileLocation\"}\n        ]\n    },\n    \"mapping\": {\n        \"Find or access an article on WeChat\": {\n            \"nodes\": [\"Node1\", \"Node2\", \"Node3\", \"Node4\", \"Node5\", \"Node6\", \"Node7\", \"Node8\", \"Node9\", \"Node10\", \"Node11\", \"Node12\", \"Node13\", \"Node14\", \"Node15\", \"Node16\", \"Node17\", \"Node18\", \"Node19\", \"Node20\", \"Node21\"]\n        },\n        \"Access an article using a direct link/URL\": {\n            \"nodes\": [\"Node1\", \"Node2\", \"Node6\", \"Node7\", \"Node8\", \"Node9\", \"Node10\", \"Node11\", \"Node12\", \"Node13\", \"Node14\", \"Node15\", \"Node16\", \"Node17\", \"Node18\", \"Node19\", \"Node20\", \"Node21\"]\n        },\n        \"Extract direct link from WeChat app\": {\n            \"nodes\": [\"Node6\"]\n        },\n        \"Validate and use the extracted link programmatically\": {\n            \"nodes\": [\"Node7\", \"Node8\", \"Node9\", \"Node10\", \"Node11\", \"Node12\", \"Node13\", \"Node14\", \"Node15\", \"Node16\", \"Node17\", \"Node18\", \"Node19\", \"Node20\", \"Node21\"]\n        },\n        \"Bypass login requirement for accessing WeChat articles\": {\n            \"nodes\": [\"Node8\", \"Node9\", \"Node10\"]\n        },\n        \"Use session cookies to authenticate requests\": {\n            \"nodes\": [\"Node8\", \"Node9\"]\n        },\n        \"Emulate WeChat client behavior to avoid security checks\": {\n            \"nodes\": [\"Node10\"]\n        },\n        \"Identify the start of the article content on the page\": {\n            \"nodes\": [\"Node11\", \"Node12\", \"Node13\"]\n        },\n        \"Search for prominent text blocks in the HTML structure\": {\n            \"nodes\": [\"Node11\"]\n        },\n        \"Handle dynamic content loading and encrypted text blobs\": {\n            \"nodes\": [\"Node12\"]\n        },\n        \"Extract and save specific article components\": {\n            \"nodes\": [\"Node14\", \"Node15\", \"Node16\", \"Node17\", \"Node18\", \"Node19\", \"Node20\", \"Node21\"]\n        },\n        \"Separate main title, subtitles (H2), and sub-subtitles (H3) from article content\": {\n            \"nodes\": [\"Node14\", \"Node15\", \"Node19\"]\n        },\n        \"Extract main title from the HTML structure\": {\n            \"nodes\": [\"Node14\"]\n        },\n        \"Extract H2 subtitles from the HTML structure\": {\n            \"nodes\": [\"Node15\"]\n        },\n        \"Extract H3 sub-subtitles from the HTML structure\": {\n            \"nodes\": [\"Node19\"]\n        },\n        \"Save extracted article data to a local file\": {\n            \"nodes\": [\"Node20\", \"Node21\", \"Node16\", \"Node17\", \"Node18\"]\n        },\n        \"Validate extracted components before saving\": {\n            \"nodes\": [\"Node20\"]\n        },\n        \"Generate a structured output file with clean formatting\": {\n            \"nodes\": [\"Node16\"]\n        },\n        \"Store the file in a user-accessible location\": {\n            \"nodes\": [\"Node17\", \"Node18\"]\n        },\n        \"Search for an article using keywords or account names\": {\n            \"nodes\": [\"Node3\", \"Node5\"]\n        },\n        \"Access an article from an official account (公众号)\": {\n            \"nodes\": [\"Node4\"]\n        }\n    }\n}\n```",
    "intent_tree": "{\"Find or access an article on WeChat\": {\"Access an article using a direct link/URL\": {\"Extract direct link from WeChat app\": {}, \"Validate and use the extracted link programmatically\": {\"Bypass login requirement for accessing WeChat articles\": {\"Use session cookies to authenticate requests\": {}, \"Emulate WeChat client behavior to avoid security checks\": {}}, \"Identify the start of the article content on the page\": {\"Search for prominent text blocks in the HTML structure\": {}, \"Handle dynamic content loading and encrypted text blobs\": {}}, \"Extract and save specific article components\": {\"Separate main title, subtitles (H2), and sub-subtitles (H3) from article content\": {\"Extract main title from the HTML structure\": {}, \"Extract H2 subtitles from the HTML structure\": {}, \"Extract H3 sub-subtitles from the HTML structure\": {}}, \"Save extracted article data to a local file\": {\"Validate extracted components before saving\": {}, \"Generate a structured output file with clean formatting\": {}, \"Store the file in a user-accessible location\": {}}}}}, \"Search for an article using keywords or account names\": {}, \"Access an article from an official account (公众号)\": {}}}",
    "task_graph": "{\"nodes\": [{\"id\": \"Node1\", \"description\": \"Share the direct link to a WeChat contact or use 'Share to WeChat' option in browser\"}, {\"id\": \"Node2\", \"description\": \"Open the shared link within WeChat’s in-app browser\"}, {\"id\": \"Node3\", \"description\": \"Use WeChat’s search bar to find articles by keywords, titles, or official account names\"}, {\"id\": \"Node4\", \"description\": \"Browse historical posts or use built-in search within an official account profile\"}, {\"id\": \"Node5\", \"description\": \"Use external tools like Sogou or WeChat Index for broader public article discovery\"}, {\"id\": \"Node6\", \"description\": \"Open the WeChat article and tap the ⋮ (three dots) to copy the direct link\"}, {\"id\": \"Node7\", \"description\": \"Programmatically validate and attempt to access the copied WeChat article link\"}, {\"id\": \"Node8\", \"description\": \"Extract session cookies from WeChat app using dynamic instrumentation tools\"}, {\"id\": \"Node9\", \"description\": \"Inject stolen cookies into HTTP requests to bypass login prompts\"}, {\"id\": \"Node10\", \"description\": \"Emulate WeChat client headers and device fingerprint to mimic legitimate access\"}, {\"id\": \"Node11\", \"description\": \"Parse the HTML structure to locate prominent text blocks (e.g., <div> with class 'rich_media_content')\"}, {\"id\": \"Node12\", \"description\": \"Handle cases where content is dynamically loaded or encrypted\"}, {\"id\": \"Node13\", \"description\": \"Extract and clean article text from identified HTML elements\"}, {\"id\": \"Node14\", \"description\": \"Extract main title from the HTML structure (e.g., <h1> tag)\"}, {\"id\": \"Node15\", \"description\": \"Extract subtitles from the HTML structure (e.g., <h2>, <h3> tags)\"}, {\"id\": \"Node16\", \"description\": \"Generate a structured output file with clean formatting\"}, {\"id\": \"Node17\", \"description\": \"Save the structured output file to a user-accessible location (e.g., Desktop)\"}, {\"id\": \"Node18\", \"description\": \"Notify the user of the exact file path where the output is saved\"}, {\"id\": \"Node19\", \"description\": \"Separate H2 subtitles from H3 sub-subtitles during extraction\"}, {\"id\": \"Node20\", \"description\": \"Validate extracted components (title, H2, H3, content) before saving\"}, {\"id\": \"Node21\", \"description\": \"Provide confirmation preview of extracted content before saving\"}], \"links\": [{\"source\": \"Node1\", \"target\": \"Node2\", \"type\": \"shareLink\"}, {\"source\": \"Node3\", \"target\": \"Node4\", \"type\": \"searchWithinAccount\"}, {\"source\": \"Node3\", \"target\": \"Node5\", \"type\": \"broadenSearch\"}, {\"source\": \"Node6\", \"target\": \"Node7\", \"type\": \"extractAndValidateLink\"}, {\"source\": \"Node8\", \"target\": \"Node9\", \"type\": \"cookieExtraction\"}, {\"source\": \"Node9\", \"target\": \"Node10\", \"type\": \"emulateClientBehavior\"}, {\"source\": \"Node7\", \"target\": \"Node11\", \"type\": \"parseHTMLForContent\"}, {\"source\": \"Node11\", \"target\": \"Node12\", \"type\": \"handleDynamicContent\"}, {\"source\": \"Node12\", \"target\": \"Node13\", \"type\": \"extractArticleText\"}, {\"source\": \"Node11\", \"target\": \"Node14\", \"type\": \"extractMainTitle\"}, {\"source\": \"Node11\", \"target\": \"Node15\", \"type\": \"extractSubtitles\"}, {\"source\": \"Node15\", \"target\": \"Node19\", \"type\": \"separateH2andH3\"}, {\"source\": \"Node14\", \"target\": \"Node20\", \"type\": \"validateComponents\"}, {\"source\": \"Node19\", \"target\": \"Node20\", \"type\": \"validateComponents\"}, {\"source\": \"Node13\", \"target\": \"Node20\", \"type\": \"validateComponents\"}, {\"source\": \"Node20\", \"target\": \"Node21\", \"type\": \"confirmationPreview\"}, {\"source\": \"Node21\", \"target\": \"Node16\", \"type\": \"generateStructuredOutput\"}, {\"source\": \"Node16\", \"target\": \"Node17\", \"type\": \"saveToFile\"}, {\"source\": \"Node17\", \"target\": \"Node18\", \"type\": \"notifyUserOfFileLocation\"}]}",
    "mapping": "{\"Find or access an article on WeChat\": {\"nodes\": [\"Node1\", \"Node2\", \"Node3\", \"Node4\", \"Node5\", \"Node6\", \"Node7\", \"Node8\", \"Node9\", \"Node10\", \"Node11\", \"Node12\", \"Node13\", \"Node14\", \"Node15\", \"Node16\", \"Node17\", \"Node18\", \"Node19\", \"Node20\", \"Node21\"]}, \"Access an article using a direct link/URL\": {\"nodes\": [\"Node1\", \"Node2\", \"Node6\", \"Node7\", \"Node8\", \"Node9\", \"Node10\", \"Node11\", \"Node12\", \"Node13\", \"Node14\", \"Node15\", \"Node16\", \"Node17\", \"Node18\", \"Node19\", \"Node20\", \"Node21\"]}, \"Extract direct link from WeChat app\": {\"nodes\": [\"Node6\"]}, \"Validate and use the extracted link programmatically\": {\"nodes\": [\"Node7\", \"Node8\", \"Node9\", \"Node10\", \"Node11\", \"Node12\", \"Node13\", \"Node14\", \"Node15\", \"Node16\", \"Node17\", \"Node18\", \"Node19\", \"Node20\", \"Node21\"]}, \"Bypass login requirement for accessing WeChat articles\": {\"nodes\": [\"Node8\", \"Node9\", \"Node10\"]}, \"Use session cookies to authenticate requests\": {\"nodes\": [\"Node8\", \"Node9\"]}, \"Emulate WeChat client behavior to avoid security checks\": {\"nodes\": [\"Node10\"]}, \"Identify the start of the article content on the page\": {\"nodes\": [\"Node11\", \"Node12\", \"Node13\"]}, \"Search for prominent text blocks in the HTML structure\": {\"nodes\": [\"Node11\"]}, \"Handle dynamic content loading and encrypted text blobs\": {\"nodes\": [\"Node12\"]}, \"Extract and save specific article components\": {\"nodes\": [\"Node14\", \"Node15\", \"Node16\", \"Node17\", \"Node18\", \"Node19\", \"Node20\", \"Node21\"]}, \"Separate main title, subtitles (H2), and sub-subtitles (H3) from article content\": {\"nodes\": [\"Node14\", \"Node15\", \"Node19\"]}, \"Extract main title from the HTML structure\": {\"nodes\": [\"Node14\"]}, \"Extract H2 subtitles from the HTML structure\": {\"nodes\": [\"Node15\"]}, \"Extract H3 sub-subtitles from the HTML structure\": {\"nodes\": [\"Node19\"]}, \"Save extracted article data to a local file\": {\"nodes\": [\"Node20\", \"Node21\", \"Node16\", \"Node17\", \"Node18\"]}, \"Validate extracted components before saving\": {\"nodes\": [\"Node20\"]}, \"Generate a structured output file with clean formatting\": {\"nodes\": [\"Node16\"]}, \"Store the file in a user-accessible location\": {\"nodes\": [\"Node17\", \"Node18\"]}, \"Search for an article using keywords or account names\": {\"nodes\": [\"Node3\", \"Node5\"]}, \"Access an article from an official account (公众号)\": {\"nodes\": [\"Node4\"]}}"
}