{
    "raw": "```JSON_RESULT\n{\n    \"intent_tree\": {\n        \"处理mp3文件并检查音频质量与语音转文字\": {\n            \"检查音频质量是否清晰\": {},\n            \"将语音转换为文字并保证准确性\": {}\n        }\n    },\n    \"task_graph\": {\n        \"nodes\": [\n            {\"id\": \"Node1\", \"description\": \"加载音频文件\"},\n            {\"id\": \"Node2\", \"description\": \"计算音频时长\"},\n            {\"id\": \"Node3\", \"description\": \"计算平均音量（RMS）\"},\n            {\"id\": \"Node4\", \"description\": \"计算最大振幅\"},\n            {\"id\": \"Node5\", \"description\": \"执行频谱分析（中心频率和带宽）\"},\n            {\"id\": \"Node6\", \"description\": \"检测静音比例\"},\n            {\"id\": \"Node7\", \"description\": \"生成音频质量报告\"},\n            {\"id\": \"Node8\", \"description\": \"选择语音识别模型\"},\n            {\"id\": \"Node9\", \"description\": \"使用Whisper模型进行语音转文字\"},\n            {\"id\": \"Node10\", \"description\": \"使用Google Web API进行语音转文字\"},\n            {\"id\": \"Node11\", \"description\": \"输出语音识别结果\"}\n        ],\n        \"links\": [\n            {\"source\": \"Node1\", \"target\": \"Node2\", \"type\": \"process\"},\n            {\"source\": \"Node1\", \"target\": \"Node3\", \"type\": \"process\"},\n            {\"source\": \"Node1\", \"target\": \"Node4\", \"type\": \"process\"},\n            {\"source\": \"Node1\", \"target\": \"Node5\", \"type\": \"process\"},\n            {\"source\": \"Node1\", \"target\": \"Node6\", \"type\": \"process\"},\n            {\"source\": \"Node2\", \"target\": \"Node7\", \"type\": \"generateReport\"},\n            {\"source\": \"Node3\", \"target\": \"Node7\", \"type\": \"generateReport\"},\n            {\"source\": \"Node4\", \"target\": \"Node7\", \"type\": \"generateReport\"},\n            {\"source\": \"Node5\", \"target\": \"Node7\", \"type\": \"generateReport\"},\n            {\"source\": \"Node6\", \"target\": \"Node7\", \"type\": \"generateReport\"},\n            {\"source\": \"Node7\", \"target\": \"Node8\", \"type\": \"nextStep\"},\n            {\"source\": \"Node8\", \"target\": \"Node9\", \"type\": \"useWhisper\"},\n            {\"source\": \"Node8\", \"target\": \"Node10\", \"type\": \"useGoogleAPI\"},\n            {\"source\": \"Node9\", \"target\": \"Node11\", \"type\": \"outputResult\"},\n            {\"source\": \"Node10\", \"target\": \"Node11\", \"type\": \"outputResult\"}\n        ]\n    },\n    \"mapping\": {\n        \"处理mp3文件并检查音频质量与语音转文字\": {\n            \"nodes\": [\"Node1\", \"Node2\", \"Node3\", \"Node4\", \"Node5\", \"Node6\", \"Node7\", \"Node8\", \"Node9\", \"Node10\", \"Node11\"]\n        },\n        \"检查音频质量是否清晰\": {\n            \"nodes\": [\"Node1\", \"Node2\", \"Node3\", \"Node4\", \"Node5\", \"Node6\", \"Node7\"]\n        },\n        \"将语音转换为文字并保证准确性\": {\n            \"nodes\": [\"Node8\", \"Node9\", \"Node10\", \"Node11\"]\n        }\n    }\n}\n```",
    "intent_tree": "{\"处理mp3文件并检查音频质量与语音转文字\": {\"检查音频质量是否清晰\": {}, \"将语音转换为文字并保证准确性\": {}}}",
    "task_graph": "{\"nodes\": [{\"id\": \"Node1\", \"description\": \"加载音频文件\"}, {\"id\": \"Node2\", \"description\": \"计算音频时长\"}, {\"id\": \"Node3\", \"description\": \"计算平均音量（RMS）\"}, {\"id\": \"Node4\", \"description\": \"计算最大振幅\"}, {\"id\": \"Node5\", \"description\": \"执行频谱分析（中心频率和带宽）\"}, {\"id\": \"Node6\", \"description\": \"检测静音比例\"}, {\"id\": \"Node7\", \"description\": \"生成音频质量报告\"}, {\"id\": \"Node8\", \"description\": \"选择语音识别模型\"}, {\"id\": \"Node9\", \"description\": \"使用Whisper模型进行语音转文字\"}, {\"id\": \"Node10\", \"description\": \"使用Google Web API进行语音转文字\"}, {\"id\": \"Node11\", \"description\": \"输出语音识别结果\"}], \"links\": [{\"source\": \"Node1\", \"target\": \"Node2\", \"type\": \"process\"}, {\"source\": \"Node1\", \"target\": \"Node3\", \"type\": \"process\"}, {\"source\": \"Node1\", \"target\": \"Node4\", \"type\": \"process\"}, {\"source\": \"Node1\", \"target\": \"Node5\", \"type\": \"process\"}, {\"source\": \"Node1\", \"target\": \"Node6\", \"type\": \"process\"}, {\"source\": \"Node2\", \"target\": \"Node7\", \"type\": \"generateReport\"}, {\"source\": \"Node3\", \"target\": \"Node7\", \"type\": \"generateReport\"}, {\"source\": \"Node4\", \"target\": \"Node7\", \"type\": \"generateReport\"}, {\"source\": \"Node5\", \"target\": \"Node7\", \"type\": \"generateReport\"}, {\"source\": \"Node6\", \"target\": \"Node7\", \"type\": \"generateReport\"}, {\"source\": \"Node7\", \"target\": \"Node8\", \"type\": \"nextStep\"}, {\"source\": \"Node8\", \"target\": \"Node9\", \"type\": \"useWhisper\"}, {\"source\": \"Node8\", \"target\": \"Node10\", \"type\": \"useGoogleAPI\"}, {\"source\": \"Node9\", \"target\": \"Node11\", \"type\": \"outputResult\"}, {\"source\": \"Node10\", \"target\": \"Node11\", \"type\": \"outputResult\"}]}",
    "mapping": "{\"处理mp3文件并检查音频质量与语音转文字\": {\"nodes\": [\"Node1\", \"Node2\", \"Node3\", \"Node4\", \"Node5\", \"Node6\", \"Node7\", \"Node8\", \"Node9\", \"Node10\", \"Node11\"]}, \"检查音频质量是否清晰\": {\"nodes\": [\"Node1\", \"Node2\", \"Node3\", \"Node4\", \"Node5\", \"Node6\", \"Node7\"]}, \"将语音转换为文字并保证准确性\": {\"nodes\": [\"Node8\", \"Node9\", \"Node10\", \"Node11\"]}}"
}