{
    "raw": "```JSON_RESULT\n{\n    \"intent_tree\": {\n        \"定位并验证音频文件的可用性\": {\n            \"定位音频文件\": {\n                \"在桌面上搜索音频文件\": {\n                    \"扫描桌面所有包含关键词的音频文件\": {}\n                }\n            },\n            \"验证音频文件的可用性\": {\n                \"快速检查文件属性\": {},\n                \"使用命令行工具深度验证文件完整性\": {}\n            }\n        },\n        \"将音频内容转为文字\": {\n            \"加载音频文件\": {\n                \"支持多种音频格式\": {\n                    \"自动转换非WAV格式为WAV\": {}\n                }\n            },\n            \"执行语音识别\": {\n                \"在线语音识别\": {\n                    \"调用Google Web Speech API进行识别\": {}\n                },\n                \"离线语音识别\": {\n                    \"调用PocketSphinx进行本地识别\": {}\n                },\n                \"专业级语音识别\": {\n                    \"使用Whisper模型进行高精度识别\": {}\n                }\n            },\n            \"保存识别结果\": {\n                \"将识别结果写入文本文件\": {}\n            },\n            \"处理异常情况\": {\n                \"捕获无法识别音频的错误\": {},\n                \"捕获API请求失败的错误\": {},\n                \"清理临时文件\": {}\n            }\n        },\n        \"整理和结构化识别后的文本内容\": {\n            \"智能标题识别\": {\n                \"显式规则识别标题\": {},\n                \"隐式分析识别标题\": {}\n            },\n            \"内容结构化处理\": {\n                \"正文分段和列表识别\": {},\n                \"长文本分句处理\": {}\n            },\n            \"生成目录和排版\": {\n                \"自动生成目录\": {},\n                \"增强排版功能\": {}\n            }\n        }\n    },\n    \"task_graph\": {\n        \"nodes\": [\n            {\"id\": \"Node1\", \"description\": \"进入桌面并使用模糊搜索查找音频文件\"},\n            {\"id\": \"Node2\", \"description\": \"通过文件资源管理器进行全盘搜索，筛选音频文件\"},\n            {\"id\": \"Node3\", \"description\": \"使用Spotlight搜索功能查找音频文件\"},\n            {\"id\": \"Node4\", \"description\": \"通过Finder高级搜索筛选音频文件\"},\n            {\"id\": \"Node5\", \"description\": \"右键文件查看属性以确认文件大小是否正常\"},\n            {\"id\": \"Node6\", \"description\": \"尝试使用系统自带播放器打开音频文件\"},\n            {\"id\": \"Node7\", \"description\": \"运行命令行工具file检查文件类型\"},\n            {\"id\": \"Node8\", \"description\": \"运行ffmpeg检测音频文件的完整性\"},\n            {\"id\": \"Node9\", \"description\": \"检查回收站或废纸篓中是否有误删的音频文件\"},\n            {\"id\": \"Node10\", \"description\": \"使用数据恢复工具扫描丢失的音频文件\"},\n            {\"id\": \"Node11\", \"description\": \"扫描桌面所有包含关键词的音频文件\"},\n            {\"id\": \"Node12\", \"description\": \"快速检查文件大小合理性\"},\n            {\"id\": \"Node13\", \"description\": \"使用ffmpeg进行深度验证\"},\n            {\"id\": \"Node14\", \"description\": \"加载音频文件并检测格式\"},\n            {\"id\": \"Node15\", \"description\": \"将非WAV格式音频转换为WAV格式\"},\n            {\"id\": \"Node16\", \"description\": \"调用Google Web Speech API进行语音识别\"},\n            {\"id\": \"Node17\", \"description\": \"调用PocketSphinx进行离线语音识别\"},\n            {\"id\": \"Node18\", \"description\": \"加载Whisper模型并执行语音识别\"},\n            {\"id\": \"Node19\", \"description\": \"将识别结果保存为TXT文件\"},\n            {\"id\": \"Node20\", \"description\": \"捕获并处理无法识别音频的异常\"},\n            {\"id\": \"Node21\", \"description\": \"捕获并处理API请求失败的异常\"},\n            {\"id\": \"Node22\", \"description\": \"删除临时生成的WAV文件\"},\n            {\"id\": \"Node23\", \"description\": \"预处理文本：去除多余空行并分割段落\"},\n            {\"id\": \"Node24\", \"description\": \"显式规则识别标题（基于正则表达式）\"},\n            {\"id\": \"Node25\", \"description\": \"隐式分析识别标题（基于TextRank算法）\"},\n            {\"id\": \"Node26\", \"description\": \"正文分段和列表识别\"},\n            {\"id\": \"Node27\", \"description\": \"长文本分句处理\"},\n            {\"id\": \"Node28\", \"description\": \"自动生成目录\"},\n            {\"id\": \"Node29\", \"description\": \"增强排版功能（如加粗实体词）\"}\n        ],\n        \"links\": [\n            {\"source\": \"Node1\", \"target\": \"Node5\", \"type\": \"findFileToCheck\"},\n            {\"source\": \"Node2\", \"target\": \"Node5\", \"type\": \"findFileToCheck\"},\n            {\"source\": \"Node3\", \"target\": \"Node5\", \"type\": \"findFileToCheck\"},\n            {\"source\": \"Node4\", \"target\": \"Node5\", \"type\": \"findFileToCheck\"},\n            {\"source\": \"Node5\", \"target\": \"Node6\", \"type\": \"checkSizeToPlay\"},\n            {\"source\": \"Node6\", \"target\": \"Node8\", \"type\": \"playFailedToDeepCheck\"},\n            {\"source\": \"Node7\", \"target\": \"Node8\", \"type\": \"typeCheckToDeepCheck\"},\n            {\"source\": \"Node9\", \"target\": \"Node5\", \"type\": \"recoverFileToCheck\"},\n            {\"source\": \"Node10\", \"target\": \"Node5\", \"type\": \"recoverFileToCheck\"},\n            {\"source\": \"Node11\", \"target\": \"Node12\", \"type\": \"scanToQuickCheck\"},\n            {\"source\": \"Node12\", \"target\": \"Node13\", \"type\": \"quickCheckToDeepVerify\"},\n            {\"source\": \"Node14\", \"target\": \"Node15\", \"type\": \"loadAudioToConvert\"},\n            {\"source\": \"Node15\", \"target\": \"Node16\", \"type\": \"convertToRecognize\"},\n            {\"source\": \"Node16\", \"target\": \"Node19\", \"type\": \"recognizeToSave\"},\n            {\"source\": \"Node17\", \"target\": \"Node19\", \"type\": \"recognizeToSave\"},\n            {\"source\": \"Node18\", \"target\": \"Node19\", \"type\": \"recognizeToSave\"},\n            {\"source\": \"Node20\", \"target\": \"Node22\", \"type\": \"handleErrorToClean\"},\n            {\"source\": \"Node21\", \"target\": \"Node22\", \"type\": \"handleErrorToClean\"},\n            {\"source\": \"Node19\", \"target\": \"Node23\", \"type\": \"saveToProcess\"},\n            {\"source\": \"Node23\", \"target\": \"Node24\", \"type\": \"processToTitleRule\"},\n            {\"source\": \"Node24\", \"target\": \"Node25\", \"type\": \"ruleToImplicit\"},\n            {\"source\": \"Node25\", \"target\": \"Node26\", \"type\": \"titleToContent\"},\n            {\"source\": \"Node26\", \"target\": \"Node27\", \"type\": \"contentToList\"},\n            {\"source\": \"Node27\", \"target\": \"Node28\", \"type\": \"listToTOC\"},\n            {\"source\": \"Node28\", \"target\": \"Node29\", \"type\": \"TOCToEnhance\"}\n        ]\n    },\n    \"mapping\": {\n        \"定位并验证音频文件的可用性\": {\n            \"nodes\": [\"Node1\", \"Node2\", \"Node3\", \"Node4\", \"Node5\", \"Node6\", \"Node7\", \"Node8\", \"Node9\", \"Node10\", \"Node11\", \"Node12\", \"Node13\"]\n        },\n        \"定位音频文件\": {\n            \"nodes\": [\"Node1\", \"Node2\", \"Node3\", \"Node4\", \"Node11\"]\n        },\n        \"在桌面上搜索音频文件\": {\n            \"nodes\": [\"Node1\", \"Node11\"]\n        },\n        \"扫描桌面所有包含关键词的音频文件\": {\n            \"nodes\": [\"Node11\"]\n        },\n        \"验证音频文件的可用性\": {\n            \"nodes\": [\"Node5\", \"Node6\", \"Node7\", \"Node8\", \"Node12\", \"Node13\"]\n        },\n        \"快速检查文件属性\": {\n            \"nodes\": [\"Node5\", \"Node6\", \"Node12\"]\n        },\n        \"使用命令行工具深度验证文件完整性\": {\n            \"nodes\": [\"Node7\", \"Node8\", \"Node13\"]\n        },\n        \"将音频内容转为文字\": {\n            \"nodes\": [\"Node14\", \"Node15\", \"Node16\", \"Node17\", \"Node18\", \"Node19\", \"Node20\", \"Node21\", \"Node22\"]\n        },\n        \"加载音频文件\": {\n            \"nodes\": [\"Node14\", \"Node15\"]\n        },\n        \"支持多种音频格式\": {\n            \"nodes\": [\"Node15\"]\n        },\n        \"自动转换非WAV格式为WAV\": {\n            \"nodes\": [\"Node15\"]\n        },\n        \"执行语音识别\": {\n            \"nodes\": [\"Node16\", \"Node17\", \"Node18\"]\n        },\n        \"在线语音识别\": {\n            \"nodes\": [\"Node16\"]\n        },\n        \"调用Google Web Speech API进行识别\": {\n            \"nodes\": [\"Node16\"]\n        },\n        \"离线语音识别\": {\n            \"nodes\": [\"Node17\"]\n        },\n        \"调用PocketSphinx进行本地识别\": {\n            \"nodes\": [\"Node17\"]\n        },\n        \"专业级语音识别\": {\n            \"nodes\": [\"Node18\"]\n        },\n        \"使用Whisper模型进行高精度识别\": {\n            \"nodes\": [\"Node18\"]\n        },\n        \"保存识别结果\": {\n            \"nodes\": [\"Node19\"]\n        },\n        \"将识别结果写入文本文件\": {\n            \"nodes\": [\"Node19\"]\n        },\n        \"处理异常情况\": {\n            \"nodes\": [\"Node20\", \"Node21\", \"Node22\"]\n        },\n        \"捕获无法识别音频的错误\": {\n            \"nodes\": [\"Node20\"]\n        },\n        \"捕获API请求失败的错误\": {\n            \"nodes\": [\"Node21\"]\n        },\n        \"清理临时文件\": {\n            \"nodes\": [\"Node22\"]\n        },\n        \"整理和结构化识别后的文本内容\": {\n            \"nodes\": [\"Node23\", \"Node24\", \"Node25\", \"Node26\", \"Node27\", \"Node28\", \"Node29\"]\n        },\n        \"智能标题识别\": {\n            \"nodes\": [\"Node24\", \"Node25\"]\n        },\n        \"显式规则识别标题\": {\n            \"nodes\": [\"Node24\"]\n        },\n        \"隐式分析识别标题\": {\n            \"nodes\": [\"Node25\"]\n        },\n        \"内容结构化处理\": {\n            \"nodes\": [\"Node26\", \"Node27\"]\n        },\n        \"正文分段和列表识别\": {\n            \"nodes\": [\"Node26\"]\n        },\n        \"长文本分句处理\": {\n            \"nodes\": [\"Node27\"]\n        },\n        \"生成目录和排版\": {\n            \"nodes\": [\"Node28\", \"Node29\"]\n        },\n        \"自动生成目录\": {\n            \"nodes\": [\"Node28\"]\n        },\n        \"增强排版功能\": {\n            \"nodes\": [\"Node29\"]\n        }\n    }\n}\n```",
    "intent_tree": "{\"定位并验证音频文件的可用性\": {\"定位音频文件\": {\"在桌面上搜索音频文件\": {\"扫描桌面所有包含关键词的音频文件\": {}}}, \"验证音频文件的可用性\": {\"快速检查文件属性\": {}, \"使用命令行工具深度验证文件完整性\": {}}}, \"将音频内容转为文字\": {\"加载音频文件\": {\"支持多种音频格式\": {\"自动转换非WAV格式为WAV\": {}}}, \"执行语音识别\": {\"在线语音识别\": {\"调用Google Web Speech API进行识别\": {}}, \"离线语音识别\": {\"调用PocketSphinx进行本地识别\": {}}, \"专业级语音识别\": {\"使用Whisper模型进行高精度识别\": {}}}, \"保存识别结果\": {\"将识别结果写入文本文件\": {}}, \"处理异常情况\": {\"捕获无法识别音频的错误\": {}, \"捕获API请求失败的错误\": {}, \"清理临时文件\": {}}}, \"整理和结构化识别后的文本内容\": {\"智能标题识别\": {\"显式规则识别标题\": {}, \"隐式分析识别标题\": {}}, \"内容结构化处理\": {\"正文分段和列表识别\": {}, \"长文本分句处理\": {}}, \"生成目录和排版\": {\"自动生成目录\": {}, \"增强排版功能\": {}}}}",
    "task_graph": "{\"nodes\": [{\"id\": \"Node1\", \"description\": \"进入桌面并使用模糊搜索查找音频文件\"}, {\"id\": \"Node2\", \"description\": \"通过文件资源管理器进行全盘搜索，筛选音频文件\"}, {\"id\": \"Node3\", \"description\": \"使用Spotlight搜索功能查找音频文件\"}, {\"id\": \"Node4\", \"description\": \"通过Finder高级搜索筛选音频文件\"}, {\"id\": \"Node5\", \"description\": \"右键文件查看属性以确认文件大小是否正常\"}, {\"id\": \"Node6\", \"description\": \"尝试使用系统自带播放器打开音频文件\"}, {\"id\": \"Node7\", \"description\": \"运行命令行工具file检查文件类型\"}, {\"id\": \"Node8\", \"description\": \"运行ffmpeg检测音频文件的完整性\"}, {\"id\": \"Node9\", \"description\": \"检查回收站或废纸篓中是否有误删的音频文件\"}, {\"id\": \"Node10\", \"description\": \"使用数据恢复工具扫描丢失的音频文件\"}, {\"id\": \"Node11\", \"description\": \"扫描桌面所有包含关键词的音频文件\"}, {\"id\": \"Node12\", \"description\": \"快速检查文件大小合理性\"}, {\"id\": \"Node13\", \"description\": \"使用ffmpeg进行深度验证\"}, {\"id\": \"Node14\", \"description\": \"加载音频文件并检测格式\"}, {\"id\": \"Node15\", \"description\": \"将非WAV格式音频转换为WAV格式\"}, {\"id\": \"Node16\", \"description\": \"调用Google Web Speech API进行语音识别\"}, {\"id\": \"Node17\", \"description\": \"调用PocketSphinx进行离线语音识别\"}, {\"id\": \"Node18\", \"description\": \"加载Whisper模型并执行语音识别\"}, {\"id\": \"Node19\", \"description\": \"将识别结果保存为TXT文件\"}, {\"id\": \"Node20\", \"description\": \"捕获并处理无法识别音频的异常\"}, {\"id\": \"Node21\", \"description\": \"捕获并处理API请求失败的异常\"}, {\"id\": \"Node22\", \"description\": \"删除临时生成的WAV文件\"}, {\"id\": \"Node23\", \"description\": \"预处理文本：去除多余空行并分割段落\"}, {\"id\": \"Node24\", \"description\": \"显式规则识别标题（基于正则表达式）\"}, {\"id\": \"Node25\", \"description\": \"隐式分析识别标题（基于TextRank算法）\"}, {\"id\": \"Node26\", \"description\": \"正文分段和列表识别\"}, {\"id\": \"Node27\", \"description\": \"长文本分句处理\"}, {\"id\": \"Node28\", \"description\": \"自动生成目录\"}, {\"id\": \"Node29\", \"description\": \"增强排版功能（如加粗实体词）\"}], \"links\": [{\"source\": \"Node1\", \"target\": \"Node5\", \"type\": \"findFileToCheck\"}, {\"source\": \"Node2\", \"target\": \"Node5\", \"type\": \"findFileToCheck\"}, {\"source\": \"Node3\", \"target\": \"Node5\", \"type\": \"findFileToCheck\"}, {\"source\": \"Node4\", \"target\": \"Node5\", \"type\": \"findFileToCheck\"}, {\"source\": \"Node5\", \"target\": \"Node6\", \"type\": \"checkSizeToPlay\"}, {\"source\": \"Node6\", \"target\": \"Node8\", \"type\": \"playFailedToDeepCheck\"}, {\"source\": \"Node7\", \"target\": \"Node8\", \"type\": \"typeCheckToDeepCheck\"}, {\"source\": \"Node9\", \"target\": \"Node5\", \"type\": \"recoverFileToCheck\"}, {\"source\": \"Node10\", \"target\": \"Node5\", \"type\": \"recoverFileToCheck\"}, {\"source\": \"Node11\", \"target\": \"Node12\", \"type\": \"scanToQuickCheck\"}, {\"source\": \"Node12\", \"target\": \"Node13\", \"type\": \"quickCheckToDeepVerify\"}, {\"source\": \"Node14\", \"target\": \"Node15\", \"type\": \"loadAudioToConvert\"}, {\"source\": \"Node15\", \"target\": \"Node16\", \"type\": \"convertToRecognize\"}, {\"source\": \"Node16\", \"target\": \"Node19\", \"type\": \"recognizeToSave\"}, {\"source\": \"Node17\", \"target\": \"Node19\", \"type\": \"recognizeToSave\"}, {\"source\": \"Node18\", \"target\": \"Node19\", \"type\": \"recognizeToSave\"}, {\"source\": \"Node20\", \"target\": \"Node22\", \"type\": \"handleErrorToClean\"}, {\"source\": \"Node21\", \"target\": \"Node22\", \"type\": \"handleErrorToClean\"}, {\"source\": \"Node19\", \"target\": \"Node23\", \"type\": \"saveToProcess\"}, {\"source\": \"Node23\", \"target\": \"Node24\", \"type\": \"processToTitleRule\"}, {\"source\": \"Node24\", \"target\": \"Node25\", \"type\": \"ruleToImplicit\"}, {\"source\": \"Node25\", \"target\": \"Node26\", \"type\": \"titleToContent\"}, {\"source\": \"Node26\", \"target\": \"Node27\", \"type\": \"contentToList\"}, {\"source\": \"Node27\", \"target\": \"Node28\", \"type\": \"listToTOC\"}, {\"source\": \"Node28\", \"target\": \"Node29\", \"type\": \"TOCToEnhance\"}]}",
    "mapping": "{\"定位并验证音频文件的可用性\": {\"nodes\": [\"Node1\", \"Node2\", \"Node3\", \"Node4\", \"Node5\", \"Node6\", \"Node7\", \"Node8\", \"Node9\", \"Node10\", \"Node11\", \"Node12\", \"Node13\"]}, \"定位音频文件\": {\"nodes\": [\"Node1\", \"Node2\", \"Node3\", \"Node4\", \"Node11\"]}, \"在桌面上搜索音频文件\": {\"nodes\": [\"Node1\", \"Node11\"]}, \"扫描桌面所有包含关键词的音频文件\": {\"nodes\": [\"Node11\"]}, \"验证音频文件的可用性\": {\"nodes\": [\"Node5\", \"Node6\", \"Node7\", \"Node8\", \"Node12\", \"Node13\"]}, \"快速检查文件属性\": {\"nodes\": [\"Node5\", \"Node6\", \"Node12\"]}, \"使用命令行工具深度验证文件完整性\": {\"nodes\": [\"Node7\", \"Node8\", \"Node13\"]}, \"将音频内容转为文字\": {\"nodes\": [\"Node14\", \"Node15\", \"Node16\", \"Node17\", \"Node18\", \"Node19\", \"Node20\", \"Node21\", \"Node22\"]}, \"加载音频文件\": {\"nodes\": [\"Node14\", \"Node15\"]}, \"支持多种音频格式\": {\"nodes\": [\"Node15\"]}, \"自动转换非WAV格式为WAV\": {\"nodes\": [\"Node15\"]}, \"执行语音识别\": {\"nodes\": [\"Node16\", \"Node17\", \"Node18\"]}, \"在线语音识别\": {\"nodes\": [\"Node16\"]}, \"调用Google Web Speech API进行识别\": {\"nodes\": [\"Node16\"]}, \"离线语音识别\": {\"nodes\": [\"Node17\"]}, \"调用PocketSphinx进行本地识别\": {\"nodes\": [\"Node17\"]}, \"专业级语音识别\": {\"nodes\": [\"Node18\"]}, \"使用Whisper模型进行高精度识别\": {\"nodes\": [\"Node18\"]}, \"保存识别结果\": {\"nodes\": [\"Node19\"]}, \"将识别结果写入文本文件\": {\"nodes\": [\"Node19\"]}, \"处理异常情况\": {\"nodes\": [\"Node20\", \"Node21\", \"Node22\"]}, \"捕获无法识别音频的错误\": {\"nodes\": [\"Node20\"]}, \"捕获API请求失败的错误\": {\"nodes\": [\"Node21\"]}, \"清理临时文件\": {\"nodes\": [\"Node22\"]}, \"整理和结构化识别后的文本内容\": {\"nodes\": [\"Node23\", \"Node24\", \"Node25\", \"Node26\", \"Node27\", \"Node28\", \"Node29\"]}, \"智能标题识别\": {\"nodes\": [\"Node24\", \"Node25\"]}, \"显式规则识别标题\": {\"nodes\": [\"Node24\"]}, \"隐式分析识别标题\": {\"nodes\": [\"Node25\"]}, \"内容结构化处理\": {\"nodes\": [\"Node26\", \"Node27\"]}, \"正文分段和列表识别\": {\"nodes\": [\"Node26\"]}, \"长文本分句处理\": {\"nodes\": [\"Node27\"]}, \"生成目录和排版\": {\"nodes\": [\"Node28\", \"Node29\"]}, \"自动生成目录\": {\"nodes\": [\"Node28\"]}, \"增强排版功能\": {\"nodes\": [\"Node29\"]}}"
}